Metadata-Version: 2.1
Name: my_road
Version: 2.0.2
Summary: long Road or not????
Author: k0ng999
Author-email: baydar_14@mail.ru
License: MIT
License-File: LICENSE
